mulac/__init__.py
mulac-0.1.5.dist-info/LICENSE
mulac-0.1.5.dist-info/METADATA
mulac-0.1.5.dist-info/WHEEL
mulac-0.1.5.dist-info/top_level.txt
mulac-0.1.5.dist-info/RECORD
