Metadata-Version: 2.1
Name: mulac
Version: 0.1.5
Summary: A simple way to distribute the computing work among a group of process-independent (or thread-independent) agents.
Author-email: NiL <csningli@qq.com>
License: MIT License        
Project-URL: Homepage, https://github.com/csningli/multi-agent-comp
Keywords: mulac
Classifier: License :: OSI Approved :: MIT License
Classifier: Programming Language :: Python
Classifier: Programming Language :: Python :: 3
Requires-Python: >=3.7.7
License-File: LICENSE
Requires-Dist: pyzmq (>=22.3.0)
